cloudpunch/__init__.py
cloudpunch/accelerator.py
cloudpunch/app.py
cloudpunch/cleanup.py
cloudpunch/configuration.py
cloudpunch/environment.py
cloudpunch/post.py
cloudpunch/version
cloudpunch/control/__init__.py
cloudpunch/control/cp_control.py
cloudpunch/master/__init__.py
cloudpunch/master/cp_master.py
cloudpunch/ostlib/__init__.py
cloudpunch/ostlib/credentials.py
cloudpunch/ostlib/exceptions.py
cloudpunch/ostlib/osceilometer.py
cloudpunch/ostlib/oscompute.py
cloudpunch/ostlib/osheat.py
cloudpunch/ostlib/osimage.py
cloudpunch/ostlib/osnetwork.py
cloudpunch/ostlib/osswift.py
cloudpunch/ostlib/osuser.py
cloudpunch/ostlib/osvolume.py
cloudpunch/slave/__init__.py
cloudpunch/slave/cp_slave.py
cloudpunch/slave/fio.py
cloudpunch/slave/flaskapp.py
cloudpunch/slave/iperf.py
cloudpunch/slave/jmeter-test.jmx
cloudpunch/slave/jmeter.py
cloudpunch/slave/ping.py
cloudpunch/slave/stress.py
cloudpunch/slave/sysinfo.py
cloudpunch/utils/__init__.py
cloudpunch/utils/config.py
cloudpunch/utils/exceptions.py
cloudpunch/utils/metrics.py
cloudpunch/utils/network.py
cloudpunch/utils/sysinfo.py
cloudpunch/worker/__init__.py
cloudpunch/worker/cp_worker.py
cloudpunch/worker/fio.py
cloudpunch/worker/flaskapp.py
cloudpunch/worker/iperf.py
cloudpunch/worker/jmeter-test.jmx
cloudpunch/worker/jmeter.py
cloudpunch/worker/ping.py
cloudpunch/worker/stress.py
cloudpunch/worker/swift.py
cloudpunch-1.5.0.dist-info/DESCRIPTION.rst
cloudpunch-1.5.0.dist-info/METADATA
cloudpunch-1.5.0.dist-info/RECORD
cloudpunch-1.5.0.dist-info/WHEEL
cloudpunch-1.5.0.dist-info/entry_points.txt
cloudpunch-1.5.0.dist-info/metadata.json
cloudpunch-1.5.0.dist-info/top_level.txt
