Metadata-Version: 2.0
Name: cloudpunch
Version: 1.5.0
Summary: Framework for OpenStack performance testing at scale
Home-page: https://github.com/target/cloudpunch
Author: Jacob Lube
Author-email: jacob.lube@target.com
License: UNKNOWN
Keywords: OpenStack cloudpunch performance
Platform: UNKNOWN
Classifier: Development Status :: 5 - Production/Stable
Classifier: Environment :: OpenStack
Classifier: Intended Audience :: Developers
Classifier: Intended Audience :: Information Technology
Classifier: Intended Audience :: System Administrators
Classifier: License :: OSI Approved :: MIT License
Classifier: Operating System :: Unix
Classifier: Operating System :: MacOS
Classifier: Programming Language :: Python
Classifier: Programming Language :: Python :: 2
Classifier: Programming Language :: Python :: 2.7
Requires-Dist: flask (>=0.12)
Requires-Dist: redis (>=2.10.5)
Requires-Dist: requests (>=2.18.1)
Requires-Dist: tabulate (>=0.7.7)
Requires-Dist: futures (>=3.0.5)
Requires-Dist: pyyaml (>=3.12)
Requires-Dist: python-keystoneclient (>=3.12.0)
Requires-Dist: python-novaclient (>=9.0.1)
Requires-Dist: python-neutronclient (>=6.3.0)
Requires-Dist: python-cinderclient (>=2.2.0)
Requires-Dist: python-glanceclient (>=2.7.0)
Requires-Dist: xmltodict (>=0.10.2)
Requires-Dist: gunicorn (>=19.7.1)
Requires-Dist: plotly (>=2.0.10)
Requires-Dist: Babel (==2.3.4)
